__init__.py
base_connection.py
device_selector.py
inventory.py
LICENSE
pyproject.toml
netscud-1.1.0.dist-info/LICENSE
netscud-1.1.0.dist-info/WHEEL
netscud-1.1.0.dist-info/METADATA
netscud-1.1.0.dist-info/RECORD
