Metadata-Version: 2.1
Name: netscud
Version: 1.1.0
Summary: Network device Asynchronous python library
Home-page: https://github.com/ericorain/netscud
License: Apache-2.0
Author: ericorain
Author-email: ericorain@hotmail.com
Requires-Python: >=3.8,<4.0
Classifier: License :: OSI Approved :: Apache Software License
Classifier: Programming Language :: Python :: 3
Classifier: Programming Language :: Python :: 3.8
Classifier: Programming Language :: Python :: 3.9
Requires-Dist: asyncssh (>=2.4.2,<3.0.0)
Requires-Dist: pyyaml (>=5.3.1,<6.0.0)
Project-URL: Documentation, https://netscud.readthedocs.io/en/latest/
